<?xml version="1.0" encoding="utf-8" ?>
<dwsync>
<file name="CHANGELOG.TXT" server="C:/xampp/htdocs/Sarlimax-SSM/" local="129323034674062500" remote="129323034670000000" />
<file name="CholeskyDecomposition.php" server="C:/xampp/htdocs/Sarlimax-SSM/" local="129323034674375000" remote="129323034670000000" />
<file name="EigenvalueDecomposition.php" server="C:/xampp/htdocs/Sarlimax-SSM/" local="129323034679375000" remote="129323034670000000" />
<file name="LUDecomposition.php" server="C:/xampp/htdocs/Sarlimax-SSM/" local="129323034684375000" remote="129323034680000000" />
<file name="Matrix.php" server="C:/xampp/htdocs/Sarlimax-SSM/" local="129323034685000000" remote="129323034680000000" />
<file name="QRDecomposition.php" server="C:/xampp/htdocs/Sarlimax-SSM/" local="129323034685781250" remote="129323034680000000" />
<file name="SingularValueDecomposition.php" server="C:/xampp/htdocs/Sarlimax-SSM/" local="129323034686406250" remote="129323034680000000" />
<file name="CHANGELOG.TXT" server="C:/xampp/htdocs/Saralimax-SSM/" local="129323034674062500" remote="129323034670000000" />
<file name="CholeskyDecomposition.php" server="C:/xampp/htdocs/Saralimax-SSM/" local="129323034674375000" remote="129323034670000000" />
<file name="EigenvalueDecomposition.php" server="C:/xampp/htdocs/Saralimax-SSM/" local="129323034679375000" remote="129323034670000000" />
<file name="LUDecomposition.php" server="C:/xampp/htdocs/Saralimax-SSM/" local="129323034684375000" remote="129323034680000000" />
<file name="Matrix.php" server="C:/xampp/htdocs/Saralimax-SSM/" local="129323034685000000" remote="129323034680000000" />
<file name="QRDecomposition.php" server="C:/xampp/htdocs/Saralimax-SSM/" local="129323034685781250" remote="129323034680000000" />
<file name="SingularValueDecomposition.php" server="C:/xampp/htdocs/Saralimax-SSM/" local="129323034686406250" remote="129323034680000000" />
<file name="CHANGELOG.TXT" server="D:/websites/SaraliMax-SSM/" local="129323034674062500" remote="129323034670000000" />
<file name="CholeskyDecomposition.php" server="D:/websites/SaraliMax-SSM/" local="129323034674375000" remote="129323034670000000" />
<file name="EigenvalueDecomposition.php" server="D:/websites/SaraliMax-SSM/" local="129323034679375000" remote="129323034670000000" />
<file name="LUDecomposition.php" server="D:/websites/SaraliMax-SSM/" local="129323034684375000" remote="129323034680000000" />
<file name="Matrix.php" server="D:/websites/SaraliMax-SSM/" local="129323034685000000" remote="129323034680000000" />
<file name="QRDecomposition.php" server="D:/websites/SaraliMax-SSM/" local="129323034685781250" remote="129323034680000000" />
<file name="SingularValueDecomposition.php" server="D:/websites/SaraliMax-SSM/" local="129323034686406250" remote="129323034680000000" />
<file name="CHANGELOG.TXT" server="213.175.192.220//support/" local="129323034674062500" remote="129763373400000000" />
<file name="CholeskyDecomposition.php" server="213.175.192.220//support/" local="129323034674375000" remote="129763373400000000" />
<file name="EigenvalueDecomposition.php" server="213.175.192.220//support/" local="129323034679375000" remote="129763374000000000" />
<file name="LUDecomposition.php" server="213.175.192.220//support/" local="129323034684375000" remote="129763374000000000" />
<file name="Matrix.php" server="213.175.192.220//support/" local="129323034685000000" remote="129763374000000000" />
<file name="QRDecomposition.php" server="213.175.192.220//support/" local="129323034685781250" remote="129763374000000000" />
<file name="SingularValueDecomposition.php" server="213.175.192.220//support/" local="129323034686406250" remote="129763374000000000" />
</dwsync>